{
  "internalLinks": [
    {
      "url": "/",
      "label": "Home",
      "iconClass": "ri-home-9-fill"
    },
    {
      "url": "/about",
      "label": "About",
      "iconClass": "ri-user-3-fill"
    },
    {
      "url": "/blog",
      "label": "Blog",
      "iconClass": "ri-article-fill"
    },
    {
      "url": "/projects",
      "label": "Projects",
      "iconClass": "ri-folder-fill"
    }
  ],

  "socialLinks": [
    {
      "url": "https://astn.sh/linkedin",
      "label": "LinkedIn",
      "iconClass": "ri-linkedin-fill"
    },
    {
      "url": "https://astn.sh/discord",
      "label": "Discord",
      "iconClass": "ri-discord-fill"
    },
    {
      "url": "https://astn.sh/facebook",
      "label": "Facebook",
      "iconClass": "ri-facebook-fill"
    },
    {
      "url": "https://astn.sh/instagram",
      "label": "Instagram",
      "iconClass": "ri-instagram-fill"
    },
    {
      "url": "https://astn.sh/bluesky",
      "label": "Bluesky",
      "iconClass": "ri-bluesky-fill"
    }
  ],

  "workLinks": [
    {
      "url": "https://astn.sh/frontend-mentor",
      "label": "Frontend Mentor",
      "iconClass": "ri-pencil-ruler-2-fill"
    },
    {
      "url": "https://astn.sh/github",
      "label": "Github",
      "iconClass": "ri-github-fill"
    },
    {
      "url": "https://astn.sh/codepen",
      "label": "CodePen",
      "iconClass": "ri-codepen-fill"
    }
  ],

  "resumeLinks": [
    {
      "url": "https://astn.sh/leetcode",
      "label": "LeetCode",
      "iconClass": "ri-code-box-fill"
    },
    {
      "url": "https://astn.sh/hackerrank",
      "label": "HackerRank",
      "iconClass": "ri-terminal-box-fill"
    },
    {
      "url": "https://astn.sh/credly",
      "label": "Credly",
      "iconClass": "ri-award-fill"
    }
  ]
}
